feacher/__init__.py
feacher/dataloader.py
feacher/feacher.py
feacher/feature_extractor.py
feacher/model.py
feacher/preprocess.py
feacher-0.0.4.dist-info/LICENCE
feacher-0.0.4.dist-info/METADATA
feacher-0.0.4.dist-info/WHEEL
feacher-0.0.4.dist-info/top_level.txt
feacher-0.0.4.dist-info/RECORD
